{
  "reconciled_through_commit": "6d81da590a12bd09bb8d0e282c042aa03d755a94",
  "composer_contract": "COMPOSER.md v0.8",
  "application_surface": {
    "roots": [
      "templates",
      "public/assets"
    ],
    "files": [
      "USER.md",
      "ADMIN.md",
      "COMMUNITY.md",
      "COMPOSER.md",
      "src/Core/FeatureFlags.php"
    ],
    "extensions": [
      "php",
      "css",
      "js"
    ],
    "excluded": [
      "public/assets/imladris.css"
    ],
    "sha256": "cb41bdf8bf7d9954c1f9f196a1bbc21b045055b35dfb943d2940678f3e982e98"
  }
}
